fabricator/__init__.py
fabricator/__version__.py
fabricator/exc.py
fabricator/extras.py
fabricator/fabricator.py
fabricate_it-1.1.0.dist-info/LICENSE
fabricate_it-1.1.0.dist-info/METADATA
fabricate_it-1.1.0.dist-info/WHEEL
fabricate_it-1.1.0.dist-info/top_level.txt
fabricate_it-1.1.0.dist-info/RECORD
