Metadata-Version: 2.1
Name: fabricate-it
Version: 1.1.0
Summary: A library that makes creating API clients simple and declarative
Home-page: https://github.com/boichee/fabricator
Author: Brett Levenson
Author-email: blevenson@apple.com
License: UNKNOWN
Platform: UNKNOWN
Classifier: Development Status :: 4 - Beta
Classifier: Operating System :: MacOS :: MacOS X
Classifier: Operating System :: POSIX
Classifier: Topic :: Software Development
Classifier: Programming Language :: Python :: 2.7
Classifier: Programming Language :: Python :: 3.6
Classifier: Intended Audience :: Developers
Requires-Dist: requests
Requires-Dist: six
Requires-Dist: future
Requires-Dist: aenum
